desktop.ini
sldt/__init__.py
sldt/desktop.ini
sldt/sldt.py
sldt-1.0.4.dist-info/METADATA
sldt-1.0.4.dist-info/WHEEL
sldt-1.0.4.dist-info/desktop.ini
sldt-1.0.4.dist-info/top_level.txt
sldt-1.0.4.dist-info/RECORD
