Metadata-Version: 2.1
Name: sldt
Version: 1.0.4
Summary: Save your files with current date time appended; load the newest back without specifying file name everytime
Home-page: https://github.com/tll549/sldt
Author: tll549
Author-email: el@tll.tl
License: MIT
Platform: UNKNOWN
Classifier: Programming Language :: Python :: 3
Classifier: License :: OSI Approved :: MIT License
Classifier: Operating System :: OS Independent
